Recosso/__init__.py
recosso-0.1.0.dist-info/LICENSE.txt
recosso-0.1.0.dist-info/METADATA
recosso-0.1.0.dist-info/WHEEL
recosso-0.1.0.dist-info/top_level.txt
recosso-0.1.0.dist-info/RECORD
