Metadata-Version: 1.1
Name: recosso
Version: 0.1.0
Summary: Official package of recosso
Home-page: UNKNOWN
Author: Himanshu Sahrawat
Author-email: hsdsahrawat@gmail.com
License: MIT
Keywords: recosso
Platform: UNKNOWN
Classifier: Development Status :: 5 - Production/Stable
Classifier: Intended Audience :: Education
Classifier: License :: OSI Approved :: MIT License
Classifier: Programming Language :: Python :: 3
